ape_tx/__init__.py
ape_tx/_cli.py
ape_tx/options.py
ape_tx/py.typed
ape_tx/utils.py
ape_tx/version.py
ape_tx-0.8.0.dist-info/licenses/LICENSE
ape_tx-0.8.0.dist-info/METADATA
ape_tx-0.8.0.dist-info/WHEEL
ape_tx-0.8.0.dist-info/entry_points.txt
ape_tx-0.8.0.dist-info/top_level.txt
ape_tx-0.8.0.dist-info/RECORD
